{"af": 418, "am": 0, "ar": 5980, "az": 182, "bg": 4515485, "bn": 2162292, "ca": 45, "cs": 152248, "da": 948257, "de": 3452343, "el": 32844, "en-pt": 10755649, "es": 7751967, "et": 154615, "fa": 29, "fa-af": 2445, "fi": 34224, "fil": 0, "fr": 4516811, "gu": 0, "he": 89073, "hi": 1576657, "hr": 30148, "ht": 1, "hu": 168467, "hy": 74188, "id": 18005, "it": 1336580, "ja": 891644, "ka": 3439852, "kn": 12, "ko": 2660478, "ky": 0, "lol": 5784, "lt": 27, "lv": 157272, "mn": 1086809, "mr": 0, "ms": 727, "my": 0, "nb": 1462917, "nl": 1431202, "nn": 0, "or": 2, "pl": 5296950, "pt": 5876802, "pt-pt": 1482062, "ro": 346402, "ru": 22287, "rw": 0, "si": 6, "sk": 204, "sl": 2, "sq": 58352, "sr": 513065, "sv": 290148, "sw": 466303, "ta": 2686, "te": 363, "th": 9923, "tr": 4956698, "uk": 3361, "ur": 1847, "uz": 913, "vi": 38, "xh": 2687, "zh-hans": 149711, "zh-hant": 31487, "zu": 2}