{"af": 418, "am": 0, "ar": 5983, "az": 182, "bg": 4538675, "bn": 2178687, "ca": 45, "cs": 151992, "da": 946262, "de": 3480757, "el": 31887, "en-pt": 10840366, "es": 7830492, "et": 154502, "fa": 29, "fa-af": 2445, "fi": 34124, "fil": 0, "fr": 4548971, "gu": 0, "he": 88219, "hi": 1574863, "hr": 30148, "ht": 1, "hu": 174705, "hy": 155982, "id": 18005, "it": 1347603, "ja": 899958, "ka": 3437890, "kn": 12, "ko": 2706598, "ky": 0, "lol": 5784, "lt": 27, "lv": 157102, "mn": 1089518, "mr": 0, "ms": 727, "my": 0, "nb": 1463234, "nl": 1432164, "nn": 0, "or": 2, "pl": 5384494, "pt": 6010301, "pt-pt": 1497891, "ro": 370961, "ru": 22303, "rw": 0, "si": 6, "sk": 204, "sl": 2, "sq": 225496, "sr": 511634, "sv": 289450, "sw": 466303, "ta": 2781, "te": 363, "th": 9923, "tr": 4991170, "uk": 3361, "ur": 1847, "uz": 910, "vi": 38, "xh": 2687, "zh-hans": 159001, "zh-hant": 31471, "zu": 2}