{
    "ar": {
        "approved": 1277, 
        "translated": 4806
    }, 
    "bg": {
        "approved": 227964, 
        "translated": 248242
    }, 
    "bn": {
        "approved": 128215, 
        "translated": 142204
    }, 
    "cs": {
        "approved": 13290, 
        "translated": 30463
    }, 
    "da": {
        "approved": 82248, 
        "translated": 89916
    }, 
    "de": {
        "approved": 196767, 
        "pending_since_timestamp": 1479751260.699802, 
        "translated": 207517
    }, 
    "el": {
        "approved": 2584, 
        "translated": 10564
    }, 
    "es": {
        "approved": 367814, 
        "translated": 384862
    }, 
    "fa": {
        "approved": 3, 
        "translated": 106
    }, 
    "fa-af": {
        "approved": 31, 
        "translated": 104
    }, 
    "fr": {
        "approved": 208456, 
        "pending_since_timestamp": 1479783729.484717, 
        "translated": 220544
    }, 
    "he": {
        "approved": 10155, 
        "translated": 10718
    }, 
    "hi": {
        "approved": 95612, 
        "pending_since_timestamp": 1479717587.972522, 
        "translated": 116503
    }, 
    "hy": {
        "approved": 89, 
        "pending_since_timestamp": 1479496824.791817, 
        "translated": 5113
    }, 
    "id": {
        "approved": 2112, 
        "pending_since_timestamp": 1479559620.874208, 
        "translated": 8194
    }, 
    "it": {
        "approved": 66658, 
        "pending_since_timestamp": 1479475170.022537, 
        "translated": 118681
    }, 
    "ja": {
        "approved": 79586, 
        "translated": 118415
    }, 
    "ka": {
        "approved": 187670, 
        "pending_since_timestamp": 1479747647.776757, 
        "translated": 193089
    }, 
    "ko": {
        "approved": 148998, 
        "pending_since_timestamp": 1479711941.576047, 
        "translated": 167267
    }, 
    "lol": {
        "approved": 595, 
        "translated": 8801
    }, 
    "mn": {
        "approved": 75202, 
        "translated": 82781
    }, 
    "ms": {
        "approved": 392, 
        "translated": 1057
    }, 
    "nb": {
        "approved": 98199, 
        "translated": 101285
    }, 
    "nl": {
        "approved": 99147, 
        "pending_since_timestamp": 1479747647.776757, 
        "translated": 125895
    }, 
    "pl": {
        "approved": 253160, 
        "pending_since_timestamp": 1479765099.058388, 
        "translated": 253710
    }, 
    "pt": {
        "approved": 249330, 
        "pending_since_timestamp": 1479781647.237991, 
        "translated": 290480
    }, 
    "pt-pt": {
        "approved": 63176, 
        "translated": 90995
    }, 
    "ru": {
        "approved": 3669, 
        "pending_since_timestamp": 1479690335.913377, 
        "translated": 20780
    }, 
    "sr": {
        "approved": 54064, 
        "translated": 71885
    }, 
    "sw": {
        "approved": 12941, 
        "translated": 33851
    }, 
    "te": {
        "approved": 34, 
        "translated": 234
    }, 
    "th": {
        "approved": 1546, 
        "pending_since_timestamp": 1479559620.874208, 
        "translated": 119801
    }, 
    "tr": {
        "approved": 263562, 
        "translated": 345857
    }, 
    "uk": {
        "approved": 337, 
        "translated": 2722
    }, 
    "ur": {
        "approved": 480, 
        "translated": 1611
    }, 
    "xh": {
        "approved": 40, 
        "translated": 41
    }, 
    "zh-hans": {
        "approved": 744, 
        "translated": 5692
    }, 
    "zu": {
        "approved": 2, 
        "translated": 23
    }
}