{
    "ar": {
        "approved": 0, 
        "translated": 3764
    }, 
    "bg": {
        "approved": 66753, 
        "translated": 131748
    }, 
    "bn": {
        "approved": 15486, 
        "pending_since_timestamp": 1443019321.489911, 
        "translated": 39435
    }, 
    "cs": {
        "approved": 0, 
        "translated": 3029
    }, 
    "da": {
        "approved": 21837, 
        "translated": 68099
    }, 
    "de": {
        "approved": 91944, 
        "translated": 100172
    }, 
    "el": {
        "approved": 0, 
        "pending_since_timestamp": 1443010523.740941, 
        "translated": 6404
    }, 
    "es": {
        "approved": 181613, 
        "pending_since_timestamp": 1443021499.386454, 
        "translated": 280240
    }, 
    "fa": {
        "approved": 0, 
        "translated": 225
    }, 
    "fa-af": {
        "approved": 0, 
        "translated": 0
    }, 
    "fr": {
        "approved": 101271, 
        "pending_since_timestamp": 1443022441.837662, 
        "translated": 104581
    }, 
    "he": {
        "approved": 8707, 
        "translated": 9068
    }, 
    "hi": {
        "approved": 37307, 
        "translated": 59791
    }, 
    "hy": {
        "approved": 0, 
        "translated": 107
    }, 
    "id": {
        "approved": 0, 
        "translated": 9038
    }, 
    "it": {
        "approved": 0, 
        "translated": 41876
    }, 
    "ja": {
        "approved": 16054, 
        "pending_since_timestamp": 1443015355.076425, 
        "translated": 50419
    }, 
    "ko": {
        "approved": 81324, 
        "translated": 89395
    }, 
    "mn": {
        "approved": 0, 
        "translated": 5839
    }, 
    "ms": {
        "approved": 0, 
        "translated": 700
    }, 
    "nb": {
        "approved": 84835, 
        "translated": 87691
    }, 
    "nl": {
        "approved": 27573, 
        "pending_since_timestamp": 1443008638.097638, 
        "translated": 40083
    }, 
    "pl": {
        "approved": 108660, 
        "pending_since_timestamp": 1443021499.386454, 
        "translated": 124245
    }, 
    "pt": {
        "approved": 145164, 
        "pending_since_timestamp": 1443020498.234408, 
        "translated": 277676
    }, 
    "pt-pt": {
        "approved": 13509, 
        "pending_since_timestamp": 1443018408.427978, 
        "translated": 40522
    }, 
    "ru": {
        "approved": 0, 
        "translated": 11188
    }, 
    "sr": {
        "approved": 33026, 
        "translated": 276270
    }, 
    "sw": {
        "approved": 0, 
        "pending_since_timestamp": 1443010523.740941, 
        "translated": 11529
    }, 
    "te": {
        "approved": 0, 
        "translated": 101
    }, 
    "th": {
        "approved": 0, 
        "pending_since_timestamp": 1443019321.489911, 
        "translated": 102732
    }, 
    "tr": {
        "approved": 176503, 
        "translated": 196616
    }, 
    "uk": {
        "approved": 0, 
        "translated": 1487
    }, 
    "ur": {
        "approved": 0, 
        "translated": 1518
    }, 
    "xh": {
        "approved": 0, 
        "translated": 1
    }, 
    "zh-hans": {
        "approved": 0, 
        "translated": 4621
    }, 
    "zu": {
        "approved": 0, 
        "translated": 26
    }
}