{
    "ar": {
        "approved": 0, 
        "pending_since_timestamp": 1450259620.01205, 
        "translated": 4291
    }, 
    "bg": {
        "approved": 120154, 
        "translated": 164647
    }, 
    "bn": {
        "approved": 39556, 
        "pending_since_timestamp": 1450250819.564969, 
        "translated": 73807
    }, 
    "cs": {
        "approved": 13516, 
        "translated": 30032
    }, 
    "da": {
        "approved": 40311, 
        "pending_since_timestamp": 1450254739.630468, 
        "translated": 72947
    }, 
    "de": {
        "approved": 108844, 
        "translated": 108975
    }, 
    "el": {
        "approved": 0, 
        "translated": 6850
    }, 
    "es": {
        "approved": 201025, 
        "pending_since_timestamp": 1450259620.01205, 
        "translated": 303123
    }, 
    "fa": {
        "approved": 0, 
        "translated": 249
    }, 
    "fa-af": {
        "approved": 0, 
        "translated": 10
    }, 
    "fr": {
        "approved": 109106, 
        "pending_since_timestamp": 1450262451.52939, 
        "translated": 114974
    }, 
    "he": {
        "approved": 8582, 
        "translated": 9163
    }, 
    "hi": {
        "approved": 71770, 
        "pending_since_timestamp": 1450265892.253056, 
        "translated": 73190
    }, 
    "hy": {
        "approved": 0, 
        "translated": 132
    }, 
    "id": {
        "approved": 0, 
        "translated": 9169
    }, 
    "it": {
        "approved": 0, 
        "pending_since_timestamp": 1450247271.796479, 
        "translated": 57430
    }, 
    "ja": {
        "approved": 21739, 
        "pending_since_timestamp": 1450247271.796479, 
        "translated": 53924
    }, 
    "ko": {
        "approved": 77412, 
        "translated": 88215
    }, 
    "lol": {
        "approved": 704, 
        "translated": 5601
    }, 
    "mn": {
        "approved": 25856, 
        "pending_since_timestamp": 1450241414.211634, 
        "translated": 45425
    }, 
    "ms": {
        "approved": 0, 
        "translated": 804
    }, 
    "nb": {
        "approved": 88058, 
        "translated": 88801
    }, 
    "nl": {
        "approved": 48071, 
        "pending_since_timestamp": 1450257779.055735, 
        "translated": 73282
    }, 
    "pl": {
        "approved": 119511, 
        "pending_since_timestamp": 1450255981.320962, 
        "translated": 128389
    }, 
    "pt": {
        "approved": 160677, 
        "pending_since_timestamp": 1450265892.253056, 
        "translated": 300325
    }, 
    "pt-pt": {
        "approved": 13966, 
        "translated": 79621
    }, 
    "ru": {
        "approved": 1228, 
        "translated": 14227
    }, 
    "sr": {
        "approved": 35962, 
        "pending_since_timestamp": 1450265892.253056, 
        "translated": 299097
    }, 
    "sw": {
        "approved": 13011, 
        "translated": 32726
    }, 
    "te": {
        "approved": 0, 
        "translated": 202
    }, 
    "th": {
        "approved": 0, 
        "translated": 130106
    }, 
    "tr": {
        "approved": 173863, 
        "pending_since_timestamp": 1450261562.424625, 
        "translated": 213885
    }, 
    "uk": {
        "approved": 0, 
        "translated": 1930
    }, 
    "ur": {
        "approved": 0, 
        "translated": 1624
    }, 
    "xh": {
        "approved": 0, 
        "translated": 1
    }, 
    "zh-hans": {
        "approved": 0, 
        "pending_since_timestamp": 1450237829.474543, 
        "translated": 4321
    }, 
    "zu": {
        "approved": 0, 
        "translated": 29
    }
}