{
    "ar": {
        "approved": 160, 
        "translated": 3667
    }, 
    "bg": {
        "approved": 182598, 
        "translated": 202948
    }, 
    "bn": {
        "approved": 121456, 
        "translated": 135130
    }, 
    "cs": {
        "approved": 12229, 
        "translated": 28911
    }, 
    "da": {
        "approved": 73885, 
        "translated": 81625
    }, 
    "de": {
        "approved": 195088, 
        "translated": 197646
    }, 
    "el": {
        "approved": 868, 
        "pending_since_timestamp": 1481880597.849273, 
        "translated": 9108
    }, 
    "es": {
        "approved": 304502, 
        "translated": 323641
    }, 
    "fa": {
        "approved": 1, 
        "translated": 103
    }, 
    "fa-af": {
        "approved": 31, 
        "translated": 104
    }, 
    "fr": {
        "approved": 202750, 
        "translated": 216235
    }, 
    "he": {
        "approved": 6510, 
        "translated": 7054
    }, 
    "hi": {
        "approved": 96025, 
        "pending_since_timestamp": 1481884829.901433, 
        "translated": 115348
    }, 
    "hy": {
        "approved": 4129, 
        "translated": 9899
    }, 
    "id": {
        "approved": 532, 
        "translated": 6319
    }, 
    "it": {
        "approved": 61357, 
        "translated": 110019
    }, 
    "ja": {
        "approved": 95206, 
        "translated": 114651
    }, 
    "ka": {
        "approved": 186801, 
        "translated": 191987
    }, 
    "ko": {
        "approved": 141288, 
        "translated": 155887
    }, 
    "lol": {
        "approved": 397, 
        "translated": 8672
    }, 
    "mn": {
        "approved": 73620, 
        "translated": 81198
    }, 
    "ms": {
        "approved": 29, 
        "translated": 689
    }, 
    "nb": {
        "approved": 96236, 
        "translated": 99302
    }, 
    "nl": {
        "approved": 96805, 
        "translated": 120477
    }, 
    "pl": {
        "approved": 234243, 
        "pending_since_timestamp": 1481882519.772298, 
        "translated": 234835
    }, 
    "pt": {
        "approved": 242621, 
        "pending_since_timestamp": 1481880597.849273, 
        "translated": 280884
    }, 
    "pt-pt": {
        "approved": 60436, 
        "translated": 87795
    }, 
    "ru": {
        "approved": 1638, 
        "translated": 18145
    }, 
    "sr": {
        "approved": 50985, 
        "translated": 68769
    }, 
    "sw": {
        "approved": 11652, 
        "translated": 31798
    }, 
    "te": {
        "approved": 16, 
        "translated": 214
    }, 
    "th": {
        "approved": 316, 
        "translated": 117760
    }, 
    "tr": {
        "approved": 234358, 
        "translated": 318732
    }, 
    "uk": {
        "approved": 98, 
        "translated": 2481
    }, 
    "ur": {
        "approved": 92, 
        "translated": 1204
    }, 
    "xh": {
        "approved": 40, 
        "translated": 40
    }, 
    "zh-hans": {
        "approved": 128, 
        "translated": 5042
    }, 
    "zu": {
        "approved": 1, 
        "translated": 22
    }
}