{
    "ar": {
        "approved": "0", 
        "translated": "3622"
    }, 
    "bg": {
        "approved": "1500", 
        "translated": "89967"
    }, 
    "bn": {
        "approved": "0", 
        "translated": "4818"
    }, 
    "cs": {
        "approved": "0", 
        "translated": "2804"
    }, 
    "da": {
        "approved": "21072", 
        "translated": "69968"
    }, 
    "de": {
        "approved": "20407", 
        "translated": "81347"
    }, 
    "el": {
        "approved": "0", 
        "translated": "5789"
    }, 
    "es": {
        "approved": "99396", 
        "translated": "239493"
    }, 
    "fa": {
        "approved": "0", 
        "translated": "20"
    }, 
    "fa-af": {
        "approved": "0", 
        "translated": "0"
    }, 
    "fr": {
        "approved": "89320", 
        "translated": "92651"
    }, 
    "he": {
        "approved": "223", 
        "translated": "8733"
    }, 
    "hi": {
        "approved": "22534", 
        "translated": "41776"
    }, 
    "hy": {
        "approved": "0", 
        "translated": "32"
    }, 
    "id": {
        "approved": "0", 
        "translated": "9668"
    }, 
    "it": {
        "approved": "0", 
        "translated": "29170"
    }, 
    "ja": {
        "approved": "6476", 
        "translated": "45364"
    }, 
    "mn": {
        "approved": "0", 
        "translated": "3435"
    }, 
    "ms": {
        "approved": "0", 
        "translated": "131"
    }, 
    "nb": {
        "approved": "76591", 
        "translated": "78755"
    }, 
    "nl": {
        "approved": "21825", 
        "translated": "29243"
    }, 
    "pl": {
        "approved": "92421", 
        "translated": "111415"
    }, 
    "pt": {
        "approved": "127288", 
        "translated": "237344"
    }, 
    "pt-pt": {
        "approved": "6509", 
        "translated": "18613"
    }, 
    "ru": {
        "approved": "0", 
        "translated": "7575"
    }, 
    "sr": {
        "approved": "133", 
        "translated": "25447"
    }, 
    "sw": {
        "approved": "0", 
        "translated": "1681"
    }, 
    "te": {
        "approved": "0", 
        "translated": "106"
    }, 
    "th": {
        "approved": "0", 
        "translated": "77256"
    }, 
    "tr": {
        "approved": "161625", 
        "translated": "171593"
    }, 
    "uk": {
        "approved": "0", 
        "translated": "1322"
    }, 
    "ur": {
        "approved": "0", 
        "translated": "830"
    }, 
    "xh": {
        "approved": "0", 
        "translated": "1"
    }, 
    "zh-hans": {
        "approved": "0", 
        "translated": "4649"
    }, 
    "zu": {
        "approved": "0", 
        "translated": "8"
    }
}
