{
    "ar": {
        "approved": 0, 
        "translated": 4431
    }, 
    "bg": {
        "approved": 168131, 
        "translated": 169355
    }, 
    "bn": {
        "approved": 51726, 
        "pending_since_timestamp": 1453875435.510619, 
        "translated": 88892
    }, 
    "cs": {
        "approved": 12930, 
        "translated": 30538
    }, 
    "da": {
        "approved": 38972, 
        "translated": 68475
    }, 
    "de": {
        "approved": 117875, 
        "translated": 118361
    }, 
    "el": {
        "approved": 3, 
        "translated": 6941
    }, 
    "es": {
        "approved": 198239, 
        "translated": 319881
    }, 
    "fa": {
        "approved": 0, 
        "translated": 235
    }, 
    "fa-af": {
        "approved": 0, 
        "translated": 74
    }, 
    "fr": {
        "approved": 112321, 
        "pending_since_timestamp": 1453877370.235129, 
        "translated": 119391
    }, 
    "he": {
        "approved": 8573, 
        "translated": 9401
    }, 
    "hi": {
        "approved": 64372, 
        "pending_since_timestamp": 1453879431.085494, 
        "translated": 73056
    }, 
    "hy": {
        "approved": 0, 
        "translated": 141
    }, 
    "id": {
        "approved": 0, 
        "translated": 8670
    }, 
    "it": {
        "approved": 0, 
        "translated": 74510
    }, 
    "ja": {
        "approved": 23508, 
        "translated": 54748
    }, 
    "ko": {
        "approved": 72638, 
        "pending_since_timestamp": 1453873495.262487, 
        "translated": 90793
    }, 
    "lol": {
        "approved": 616, 
        "translated": 8064
    }, 
    "mn": {
        "approved": 36098, 
        "pending_since_timestamp": 1453877370.235129, 
        "translated": 56275
    }, 
    "ms": {
        "approved": 0, 
        "translated": 827
    }, 
    "nb": {
        "approved": 84512, 
        "translated": 85601
    }, 
    "nl": {
        "approved": 47808, 
        "translated": 80566
    }, 
    "pl": {
        "approved": 130518, 
        "translated": 133867
    }, 
    "pt": {
        "approved": 150698, 
        "translated": 317055
    }, 
    "pt-pt": {
        "approved": 13951, 
        "translated": 76987
    }, 
    "ru": {
        "approved": 1233, 
        "translated": 18081
    }, 
    "sr": {
        "approved": 34802, 
        "pending_since_timestamp": 1453873495.262487, 
        "translated": 315796
    }, 
    "sw": {
        "approved": 12324, 
        "translated": 34343
    }, 
    "te": {
        "approved": 0, 
        "translated": 238
    }, 
    "th": {
        "approved": 0, 
        "translated": 125652
    }, 
    "tr": {
        "approved": 168813, 
        "pending_since_timestamp": 1453877370.235129, 
        "translated": 227929
    }, 
    "uk": {
        "approved": 0, 
        "translated": 2710
    }, 
    "ur": {
        "approved": 0, 
        "translated": 1499
    }, 
    "xh": {
        "approved": 0, 
        "translated": 1
    }, 
    "zh-hans": {
        "approved": 0, 
        "translated": 4389
    }, 
    "zu": {
        "approved": 0, 
        "translated": 32
    }
}