{
    "ar": {
        "approved": 0, 
        "translated": 4622
    }, 
    "bg": {
        "approved": 168835, 
        "pending_since_timestamp": 1461329591.026903, 
        "translated": 189548
    }, 
    "bn": {
        "approved": 72436, 
        "translated": 120462
    }, 
    "cs": {
        "approved": 12587, 
        "translated": 30004
    }, 
    "da": {
        "approved": 39057, 
        "translated": 87996
    }, 
    "de": {
        "approved": 149301, 
        "translated": 149782
    }, 
    "el": {
        "approved": 257, 
        "translated": 7557
    }, 
    "es": {
        "approved": 253453, 
        "pending_since_timestamp": 1461340490.107979, 
        "translated": 369419
    }, 
    "fa": {
        "approved": 0, 
        "translated": 211
    }, 
    "fa-af": {
        "approved": 0, 
        "translated": 72
    }, 
    "fr": {
        "approved": 149854, 
        "pending_since_timestamp": 1461330930.564697, 
        "translated": 158237
    }, 
    "he": {
        "approved": 9223, 
        "translated": 9236
    }, 
    "hi": {
        "approved": 68892, 
        "translated": 87224
    }, 
    "hy": {
        "approved": 0, 
        "translated": 2829
    }, 
    "id": {
        "approved": 0, 
        "translated": 8122
    }, 
    "it": {
        "approved": 0, 
        "pending_since_timestamp": 1461329591.026903, 
        "translated": 93645
    }, 
    "ja": {
        "approved": 27588, 
        "translated": 57983
    }, 
    "ka": {
        "approved": 118845, 
        "pending_since_timestamp": 1461318984.565688, 
        "translated": 119269
    }, 
    "ko": {
        "approved": 108834, 
        "translated": 138899
    }, 
    "lol": {
        "approved": 587, 
        "translated": 7578
    }, 
    "mn": {
        "approved": 74740, 
        "translated": 82707
    }, 
    "ms": {
        "approved": 0, 
        "translated": 750
    }, 
    "nb": {
        "approved": 87986, 
        "translated": 88846
    }, 
    "nl": {
        "approved": 55370, 
        "pending_since_timestamp": 1461318984.565688, 
        "translated": 104308
    }, 
    "pl": {
        "approved": 191599, 
        "pending_since_timestamp": 1461336588.981759, 
        "translated": 191641
    }, 
    "pt": {
        "approved": 185342, 
        "translated": 366567
    }, 
    "pt-pt": {
        "approved": 17691, 
        "pending_since_timestamp": 1461323411.009715, 
        "translated": 117019
    }, 
    "ru": {
        "approved": 1175, 
        "translated": 20757
    }, 
    "sr": {
        "approved": 46871, 
        "pending_since_timestamp": 1461246377.983701, 
        "translated": 365412
    }, 
    "sw": {
        "approved": 12006, 
        "translated": 35107
    }, 
    "te": {
        "approved": 0, 
        "translated": 215
    }, 
    "th": {
        "approved": 0, 
        "translated": 126851
    }, 
    "tr": {
        "approved": 168520, 
        "pending_since_timestamp": 1461336588.981759, 
        "translated": 274838
    }, 
    "uk": {
        "approved": 0, 
        "translated": 2579
    }, 
    "ur": {
        "approved": 0, 
        "translated": 1536
    }, 
    "xh": {
        "approved": 0, 
        "translated": 1
    }, 
    "zh-hans": {
        "approved": 0, 
        "translated": 4084
    }, 
    "zu": {
        "approved": 0, 
        "translated": 23
    }
}