{
    "ar": {
        "approved": 0, 
        "translated": 4292
    }, 
    "bg": {
        "approved": 116162, 
        "translated": 167205
    }, 
    "bn": {
        "approved": 41578, 
        "pending_since_timestamp": 1452058931.12767, 
        "translated": 79848
    }, 
    "cs": {
        "approved": 13313, 
        "translated": 30071
    }, 
    "da": {
        "approved": 39267, 
        "translated": 71163
    }, 
    "de": {
        "approved": 114263, 
        "translated": 114421
    }, 
    "el": {
        "approved": 0, 
        "translated": 6883
    }, 
    "es": {
        "approved": 201925, 
        "pending_since_timestamp": 1452058931.12767, 
        "translated": 312536
    }, 
    "fa": {
        "approved": 0, 
        "translated": 249
    }, 
    "fa-af": {
        "approved": 0, 
        "translated": 10
    }, 
    "fr": {
        "approved": 109418, 
        "translated": 116200
    }, 
    "he": {
        "approved": 8547, 
        "translated": 9352
    }, 
    "hi": {
        "approved": 68484, 
        "pending_since_timestamp": 1452058931.12767, 
        "translated": 73836
    }, 
    "hy": {
        "approved": 0, 
        "translated": 132
    }, 
    "id": {
        "approved": 0, 
        "translated": 9078
    }, 
    "it": {
        "approved": 0, 
        "translated": 65586
    }, 
    "ja": {
        "approved": 23690, 
        "pending_since_timestamp": 1452058931.12767, 
        "translated": 53177
    }, 
    "ko": {
        "approved": 75110, 
        "pending_since_timestamp": 1452058931.12767, 
        "translated": 86863
    }, 
    "lol": {
        "approved": 612, 
        "translated": 5271
    }, 
    "mn": {
        "approved": 28849, 
        "pending_since_timestamp": 1452052702.885559, 
        "translated": 52162
    }, 
    "ms": {
        "approved": 0, 
        "translated": 805
    }, 
    "nb": {
        "approved": 85429, 
        "translated": 85971
    }, 
    "nl": {
        "approved": 49166, 
        "translated": 78960
    }, 
    "pl": {
        "approved": 123312, 
        "translated": 131621
    }, 
    "pt": {
        "approved": 158587, 
        "pending_since_timestamp": 1452058931.12767, 
        "translated": 309678
    }, 
    "pt-pt": {
        "approved": 13861, 
        "translated": 78895
    }, 
    "ru": {
        "approved": 1229, 
        "translated": 14227
    }, 
    "sr": {
        "approved": 35642, 
        "pending_since_timestamp": 1452058931.12767, 
        "translated": 308446
    }, 
    "sw": {
        "approved": 12684, 
        "translated": 33790
    }, 
    "te": {
        "approved": 0, 
        "translated": 226
    }, 
    "th": {
        "approved": 0, 
        "translated": 129311
    }, 
    "tr": {
        "approved": 173743, 
        "pending_since_timestamp": 1452059965.707999, 
        "translated": 222331
    }, 
    "uk": {
        "approved": 0, 
        "translated": 2696
    }, 
    "ur": {
        "approved": 0, 
        "translated": 1622
    }, 
    "xh": {
        "approved": 0, 
        "translated": 1
    }, 
    "zh-hans": {
        "approved": 0, 
        "translated": 4332
    }, 
    "zu": {
        "approved": 0, 
        "translated": 29
    }
}