{
    "ar": {
        "approved": 385, 
        "translated": 4415
    }, 
    "bg": {
        "approved": 232287, 
        "translated": 237022
    }, 
    "bn": {
        "approved": 139052, 
        "translated": 148388
    }, 
    "cs": {
        "approved": 11701, 
        "translated": 29328
    }, 
    "da": {
        "approved": 71771, 
        "translated": 91890
    }, 
    "de": {
        "approved": 213667, 
        "translated": 215229
    }, 
    "el": {
        "approved": 2054, 
        "pending_since_timestamp": 1495982914.612276, 
        "translated": 21431
    }, 
    "es": {
        "approved": 349504, 
        "translated": 365232
    }, 
    "fa": {
        "approved": 1, 
        "translated": 100
    }, 
    "fa-af": {
        "approved": 31, 
        "translated": 104
    }, 
    "fr": {
        "approved": 235373, 
        "translated": 243063
    }, 
    "he": {
        "approved": 7273, 
        "translated": 7470
    }, 
    "hi": {
        "approved": 98344, 
        "translated": 114342
    }, 
    "hy": {
        "approved": 7403, 
        "translated": 12261
    }, 
    "id": {
        "approved": 531, 
        "translated": 6458
    }, 
    "it": {
        "approved": 92944, 
        "pending_since_timestamp": 1496002895.522358, 
        "translated": 124457
    }, 
    "ja": {
        "approved": 101175, 
        "translated": 120766
    }, 
    "ka": {
        "approved": 197003, 
        "pending_since_timestamp": 1495994468.288802, 
        "translated": 204755
    }, 
    "ko": {
        "approved": 157959, 
        "translated": 172251
    }, 
    "lol": {
        "approved": 382, 
        "translated": 8549
    }, 
    "mn": {
        "approved": 81289, 
        "translated": 106423
    }, 
    "ms": {
        "approved": 29, 
        "translated": 650
    }, 
    "nb": {
        "approved": 92959, 
        "translated": 110846
    }, 
    "nl": {
        "approved": 106949, 
        "translated": 128533
    }, 
    "pl": {
        "approved": 270155, 
        "translated": 270360
    }, 
    "pt": {
        "approved": 286871, 
        "pending_since_timestamp": 1495998635.718415, 
        "translated": 322649
    }, 
    "pt-pt": {
        "approved": 87984, 
        "translated": 118048
    }, 
    "ru": {
        "approved": 1535, 
        "translated": 18457
    }, 
    "sr": {
        "approved": 50436, 
        "translated": 68089
    }, 
    "sw": {
        "approved": 49026, 
        "translated": 62631
    }, 
    "te": {
        "approved": 16, 
        "translated": 241
    }, 
    "th": {
        "approved": 303, 
        "translated": 132148
    }, 
    "tr": {
        "approved": 268827, 
        "translated": 366294
    }, 
    "uk": {
        "approved": 98, 
        "translated": 2532
    }, 
    "ur": {
        "approved": 92, 
        "translated": 1162
    }, 
    "xh": {
        "approved": 40, 
        "translated": 40
    }, 
    "zh-hans": {
        "approved": 5590, 
        "translated": 31808
    }, 
    "zu": {
        "approved": 1, 
        "translated": 20
    }
}