{
    "ar": {
        "approved": 0, 
        "translated": 3823
    }, 
    "bg": {
        "approved": 91048, 
        "translated": 156931
    }, 
    "bn": {
        "approved": 27999, 
        "pending_since_timestamp": 1447470524.045191, 
        "translated": 61758
    }, 
    "cs": {
        "approved": 13792, 
        "translated": 21503
    }, 
    "da": {
        "approved": 21917, 
        "translated": 66657
    }, 
    "de": {
        "approved": 104969, 
        "pending_since_timestamp": 1447466308.539549, 
        "translated": 105090
    }, 
    "el": {
        "approved": 0, 
        "translated": 6719
    }, 
    "es": {
        "approved": 195828, 
        "translated": 293682
    }, 
    "fa": {
        "approved": 0, 
        "translated": 223
    }, 
    "fa-af": {
        "approved": 0, 
        "translated": 1
    }, 
    "fr": {
        "approved": 106907, 
        "translated": 112013
    }, 
    "he": {
        "approved": 8661, 
        "translated": 9168
    }, 
    "hi": {
        "approved": 38628, 
        "pending_since_timestamp": 1447466308.539549, 
        "translated": 64840
    }, 
    "hy": {
        "approved": 0, 
        "translated": 117
    }, 
    "id": {
        "approved": 0, 
        "translated": 9119
    }, 
    "it": {
        "approved": 0, 
        "translated": 56422
    }, 
    "ja": {
        "approved": 19845, 
        "pending_since_timestamp": 1447466308.539549, 
        "translated": 52983
    }, 
    "ko": {
        "approved": 78579, 
        "translated": 88997
    }, 
    "lol": {
        "approved": 705, 
        "translated": 5657
    }, 
    "mn": {
        "approved": 9093, 
        "translated": 32354
    }, 
    "ms": {
        "approved": 0, 
        "translated": 794
    }, 
    "nb": {
        "approved": 86885, 
        "translated": 89392
    }, 
    "nl": {
        "approved": 42999, 
        "translated": 55452
    }, 
    "pl": {
        "approved": 115736, 
        "pending_since_timestamp": 1447466308.539549, 
        "translated": 125608
    }, 
    "pt": {
        "approved": 152356, 
        "translated": 290864
    }, 
    "pt-pt": {
        "approved": 13762, 
        "pending_since_timestamp": 1447466308.539549, 
        "translated": 74828
    }, 
    "ru": {
        "approved": 943, 
        "pending_since_timestamp": 1447466308.539549, 
        "translated": 13607
    }, 
    "sr": {
        "approved": 35650, 
        "pending_since_timestamp": 1447466308.539549, 
        "translated": 289595
    }, 
    "sw": {
        "approved": 0, 
        "pending_since_timestamp": 1447466308.539549, 
        "translated": 18662
    }, 
    "te": {
        "approved": 0, 
        "translated": 101
    }, 
    "th": {
        "approved": 0, 
        "pending_since_timestamp": 1447466308.539549, 
        "translated": 128813
    }, 
    "tr": {
        "approved": 174611, 
        "translated": 207000
    }, 
    "uk": {
        "approved": 0, 
        "translated": 1564
    }, 
    "ur": {
        "approved": 0, 
        "translated": 1536
    }, 
    "xh": {
        "approved": 0, 
        "translated": 1
    }, 
    "zh-hans": {
        "approved": 0, 
        "translated": 4307
    }, 
    "zu": {
        "approved": 0, 
        "translated": 29
    }
}